wurzel/__init__.py
wurzel/exceptions.py
wurzel/py.typed
wurzel/backend/__init__.py
wurzel/backend/backend.py
wurzel/backend/backend_argo.py
wurzel/backend/backend_dvc.py
wurzel/backend/values.py
wurzel/cli/__init__.py
wurzel/cli/_main.py
wurzel/cli/cmd_env.py
wurzel/cli/cmd_generate.py
wurzel/cli/cmd_inspect.py
wurzel/cli/cmd_run.py
wurzel/cli/logger.py
wurzel/datacontract/__init__.py
wurzel/datacontract/common.py
wurzel/datacontract/datacontract.py
wurzel/path/__init__.py
wurzel/path/path.py
wurzel/step/__init__.py
wurzel/step/history.py
wurzel/step/self_consuming_step.py
wurzel/step/settings.py
wurzel/step/step.py
wurzel/step/typed_step.py
wurzel/step_executor/__init__.py
wurzel/step_executor/base_executor.py
wurzel/step_executor/prometheus_executor.py
wurzel/step_executor/settings.py
wurzel/steps/__init__.py
wurzel/steps/data.py
wurzel/steps/duplication.py
wurzel/steps/manual_markdown.py
wurzel/steps/splitter.py
wurzel/steps/decagon/__init__.py
wurzel/steps/decagon/data.py
wurzel/steps/decagon/settings.py
wurzel/steps/decagon/step.py
wurzel/steps/docling/__init__.py
wurzel/steps/docling/docling_step.py
wurzel/steps/docling/settings.py
wurzel/steps/embedding/__init__.py
wurzel/steps/embedding/huggingface.py
wurzel/steps/embedding/settings.py
wurzel/steps/embedding/step.py
wurzel/steps/embedding/step_multivector.py
wurzel/steps/milvus/__init__.py
wurzel/steps/milvus/data.py
wurzel/steps/milvus/settings.py
wurzel/steps/milvus/step.py
wurzel/steps/qdrant/__init__.py
wurzel/steps/qdrant/data.py
wurzel/steps/qdrant/settings.py
wurzel/steps/qdrant/step.py
wurzel/steps/qdrant/step_multi_vector.py
wurzel/steps/scraperapi/__init__.py
wurzel/steps/scraperapi/data.py
wurzel/steps/scraperapi/settings.py
wurzel/steps/scraperapi/step.py
wurzel/steps/sftp/__init__.py
wurzel/steps/sftp/sftp_manual_markdown.py
wurzel/utils/__init__.py
wurzel/utils/logging.py
wurzel/utils/meta_settings.py
wurzel/utils/meta_steps.py
wurzel/utils/tokenizers.py
wurzel/utils/splitters/__init__.py
wurzel-2.5.0.dist-info/licenses/LICENSE
wurzel-2.5.0.dist-info/METADATA
wurzel-2.5.0.dist-info/WHEEL
wurzel-2.5.0.dist-info/entry_points.txt
wurzel-2.5.0.dist-info/top_level.txt
wurzel-2.5.0.dist-info/RECORD
