Metadata-Version: 2.4
Name: wurzel
Version: 2.5.0
Summary: Pick, choose and chain your RAG tools in a pythonic way
Author-email: Thomas Weigel <thomas.weigel@telekom.de>, Paul Bauriegel <paul.bauriegel@telekom.de>, Maximilian Erren <maximilian.erren@telekom.de>
License: Apache License
Project-URL: Release notes, https://github.com/telekom/wurzel/releases/
Project-URL: Source, https://github.com/telekom/wurzel
Classifier: Programming Language :: Python :: 3.11
Classifier: Programming Language :: Python :: 3.12
Classifier: Intended Audience :: Developers
Classifier: Intended Audience :: Information Technology
Classifier: License :: OSI Approved :: Apache Software License
Classifier: Operating System :: OS Independent
Classifier: Topic :: Internet
Classifier: Topic :: Scientific/Engineering :: Information Analysis
Classifier: Topic :: Software Development :: Libraries :: Python Modules
Classifier: Topic :: Software Development :: Pre-processors
Classifier: Topic :: Software Development :: Version Control
Requires-Python: <3.13,>=3.11
License-File: LICENSE
Requires-Dist: tqdm==4.67.1
Requires-Dist: pandas==2.3.3
Requires-Dist: numpy<2.0.0
Requires-Dist: dvc==3.63.0
Requires-Dist: pathspec<0.13
Requires-Dist: Markdown==3.6
Requires-Dist: pydantic-settings==2.5.2
Requires-Dist: pydantic==2.*,>=2.6.4
Requires-Dist: asgi-correlation-id==4.*,>=4.3.1
Requires-Dist: prometheus-client==0.23.1
Requires-Dist: mistletoe==1.5.0
Requires-Dist: pandera==0.20.3
Requires-Dist: mdformat==0.7.22
Requires-Dist: lxml<6.1,>=5.2
Requires-Dist: pyyaml>=6.0.2
Requires-Dist: pip<26
Provides-Extra: qdrant
Requires-Dist: qdrant-client==1.15.1; extra == "qdrant"
Provides-Extra: docling
Requires-Dist: docling==2.30.0; extra == "docling"
Provides-Extra: milvus
Requires-Dist: pymilvus==2.6.3; extra == "milvus"
Provides-Extra: openai
Requires-Dist: tiktoken==0.12.0; extra == "openai"
Provides-Extra: transformers
Requires-Dist: transformers; extra == "transformers"
Provides-Extra: tlsh
Requires-Dist: py-tlsh==4.7.2; extra == "tlsh"
Provides-Extra: splitter
Requires-Dist: wurzel[wtpsplit]; extra == "splitter"
Requires-Dist: wurzel[transformers]; extra == "splitter"
Requires-Dist: wurzel[openai]; extra == "splitter"
Requires-Dist: spacy==3.7.5; extra == "splitter"
Requires-Dist: joblib>=1.4.0; extra == "splitter"
Provides-Extra: wtpsplit
Requires-Dist: wtpsplit>=2.1.6; extra == "wtpsplit"
Provides-Extra: embedding
Requires-Dist: langchain-core>=0.2.0; extra == "embedding"
Requires-Dist: requests; extra == "embedding"
Provides-Extra: scraperapi
Requires-Dist: requests; extra == "scraperapi"
Requires-Dist: joblib>=1.4.0; extra == "scraperapi"
Provides-Extra: sftp
Requires-Dist: paramiko>=3.0.0; extra == "sftp"
Provides-Extra: argo
Requires-Dist: hera>=5.20.1; extra == "argo"
Provides-Extra: lint
Requires-Dist: pylint[spelling]==3.3.7; extra == "lint"
Requires-Dist: pylint-json2html==0.5.0; extra == "lint"
Requires-Dist: pre-commit<4.6,>=4.1; extra == "lint"
Requires-Dist: reuse==6.2.0; extra == "lint"
Requires-Dist: ruff==0.14.10; extra == "lint"
Provides-Extra: test
Requires-Dist: pytest<9.1,>=8.4; extra == "test"
Requires-Dist: pytest-asyncio==0.23.*; extra == "test"
Requires-Dist: pytest-cov<8,>=4; extra == "test"
Requires-Dist: pytest-html==4.*; extra == "test"
Requires-Dist: pytest_env==1.*; extra == "test"
Requires-Dist: pytest-xdist==3.*; extra == "test"
Requires-Dist: pytest-mock==3.*; extra == "test"
Requires-Dist: requests-mock==1.*; extra == "test"
Provides-Extra: docs
Requires-Dist: mkdocstrings[python]; extra == "docs"
Requires-Dist: mkdocs-mermaid2-plugin; extra == "docs"
Requires-Dist: mkdocs-typer2; extra == "docs"
Requires-Dist: mkdocs-material>=9.4.0; extra == "docs"
Requires-Dist: mkdocs-multirepo-plugin>=0.5.3; extra == "docs"
Requires-Dist: mkdocs-git-revision-date-localized-plugin>=1.2.0; extra == "docs"
Requires-Dist: mkdocs-minify-plugin>=0.7.0; extra == "docs"
Requires-Dist: pygments>=2.16.0; extra == "docs"
Provides-Extra: all
Requires-Dist: wurzel[argo,docling,embedding,milvus,openai,qdrant,scraperapi,sftp,splitter,tlsh]; extra == "all"
Provides-Extra: dev
Requires-Dist: wurzel[all,lint,test]; extra == "dev"
Dynamic: license-file
